lxmlutil/__init__.py
lxmlutil/etree.py
lxml_util-1.0.2.dist-info/LICENSE
lxml_util-1.0.2.dist-info/METADATA
lxml_util-1.0.2.dist-info/WHEEL
lxml_util-1.0.2.dist-info/top_level.txt
lxml_util-1.0.2.dist-info/RECORD
